auggie_sdk/__init__.py
auggie_sdk/agent.py
auggie_sdk/exceptions.py
auggie_sdk/function_tools.py
auggie_sdk/listener.py
auggie_sdk/listener_adapter.py
auggie_sdk/prompt_formatter.py
auggie_sdk/acp/__init__.py
auggie_sdk/acp/claude_code_client.py
auggie_sdk/acp/client.py
auggie_sdk/acp/test_client_e2e.py
auggie_sdk/context/__init__.py
auggie_sdk/context/direct_context.py
auggie_sdk/context/filesystem_context.py
auggie_sdk/context/models.py
auggie_sdk/context/version.py
auggie_sdk/context/internal/__init__.py
auggie_sdk/context/internal/api_client.py
auggie_sdk/context/internal/blob_name_calculator.py
auggie_sdk/context/internal/credentials.py
auggie_sdk/context/internal/retry_utils.py
auggie_sdk/context/internal/search_utils.py
auggie_sdk/context/internal/session_reader.py
auggie_sdk-0.1.10.dist-info/licenses/LICENSE
auggie_sdk-0.1.10.dist-info/METADATA
auggie_sdk-0.1.10.dist-info/WHEEL
auggie_sdk-0.1.10.dist-info/top_level.txt
auggie_sdk-0.1.10.dist-info/RECORD
